README.md
setup.py
logwas.egg-info/PKG-INFO
logwas.egg-info/SOURCES.txt
logwas.egg-info/dependency_links.txt
logwas.egg-info/requires.txt
logwas.egg-info/top_level.txt
wassim/__init__.py
wassim/army_class.py
wassim/attackclass.py
wassim/board.py
wassim/chess_Engine.py
wassim/chess_GUI.py
wassim/human.py
wassim/humans_class.py
wassim/lineConsole_int.py
wassim/move.py
wassim/orcs_class.py
wassim/party_class.py
wassim/MVP/MVP.py
wassim/MVP/MVP_refractored.py
wassim/MVP/__init__.py
wassim/images/__init__.py