Metadata-Version: 2.1
Name: logwas
Version: 0.0.1
Summary: Jeu de stratégie sur plateau
Home-page: UNKNOWN
Author: Bouhdid Wassim
Author-email: <mail.wassim@hotmail.com>
License: UNKNOWN
Keywords: python,war,strategy,game,pygame
Platform: UNKNOWN
Classifier: Development Status :: 1 - Planning
Classifier: Intended Audience :: Developers
Classifier: Programming Language :: Python :: 3
Classifier: Operating System :: Microsoft :: Windows
